README
setup.py
src/__init__.py
src/customer.py
src/media.py
src/oauth.py
src/template.py
src/token.py
src/unit.py
wechatOauth.egg-info/PKG-INFO
wechatOauth.egg-info/SOURCES.txt
wechatOauth.egg-info/dependency_links.txt
wechatOauth.egg-info/top_level.txt
wechatOauth.egg-info/zip-safe