Metadata-Version: 1.1
Name: wechatOauth
Version: 0.0.8
Summary: A python SDK that use to wechat oauth verification
Home-page: https://github.com/mymusise/wechat-oauth
Author: mymusise
Author-email: mymusise1@gmail.com
License: MIT
Keywords: wechat oauth python
Platform: UNKNOWN
Classifier: License :: OSI Approved :: MIT License
Classifier: Programming Language :: Python
Classifier: Intended Audience :: Developers
Classifier: Operating System :: OS Independent
